{"schemaVersion":"1.0","appDefinitionTemplate":{"id":"/providers/Microsoft.PowerApps/apps/","type":"Microsoft.PowerApps/apps","tags":{"minimumRequiredApiVersion":"2.2.0"},"properties":{"appVersion":"2019-04-30T03:28:33Z","lifeCycleId":"Published","createdByClientVersion":{"major":3,"minor":19043,"build":16,"revision":0,"majorRevision":0,"minorRevision":0},"minClientVersion":{"major":3,"minor":19043,"build":16,"revision":0,"majorRevision":0,"minorRevision":0},"backgroundColor":"rgba(208, 52, 56, 1)","backgroundImageUri":"/10860948751991422357/Nb66d20e9-403e-47ff-bc69-4f7c0f62a320-logoSmallFile","displayName":"My first app","description":"\nThis application is quite helpful","appUris":{"documentUri":{"value":"/10860948751991422357/Nf7f50c2c-82f0-412e-b611-f563e15f4025-document.msapp","readonlyValue":"/10860948751991422357/Nf7f50c2c-82f0-412e-b611-f563e15f4025-document.msapp"},"imageUris":[]},"createdTime":"0001-01-01T00:00:00Z","lastModifiedTime":"0001-01-01T00:00:00Z","sharedGroupsCount":0,"sharedUsersCount":0,"icons":{"smallIconUri":"/10860948751991422357/N3b0e070d-182f-4123-b8b6-1e1bae54d157-small.png","mediumIconUri":"/10860948751991422357/Ncce37c50-4ca0-44f3-8447-8349bfbf0050-medium.png","largeIconUri":"/10860948751991422357/Nc14a23f1-084d-4803-83f2-86f8d0e11570-large.png","wideIconUri":"/10860948751991422357/Nc8071238-4621-437e-a17a-6fde0f7ae3bb-wide.png"},"connectionReferences":{"13c42ba5-9143-4f9c-9e49-745c2a8ed629":{"id":"8d5e7443-527c-4a75-94a1-6839dc45ea0c","displayName":"Excel","iconUri":"https://connectoricons-prod.azureedge.net/excel/icon_1.0.1018.1190.png","dataSources":["Purchases"],"dependencies":["9e2028ab-7b35-40eb-9423-ca851d9e29b1"],"dependents":[],"parameterHints":{"9e2028ab-7b35-40eb-9423-ca851d9e29b1":{"value":"fileSource"}},"isOnPremiseConnection":false,"bypassConsent":false,"dataSets":{"268EC6269C47C101!106":{"dataSources":{"Purchases":{"tableName":"Purchases"}}}},"apiTier":"Standard","isCustomApiConnection":false},"9e2028ab-7b35-40eb-9423-ca851d9e29b1":{"id":"375e6f73-6189-4d49-a765-7f8e51a0f555","displayName":"OneDrive","iconUri":"https://connectoricons-prod.azureedge.net/onedrive/icon_1.0.1046.1227.png","dataSources":[],"dependencies":[],"dependents":["13c42ba5-9143-4f9c-9e49-745c2a8ed629"],"parameterHints":{},"isOnPremiseConnection":false,"bypassConsent":false,"dataSets":{},"apiTier":"Standard","isCustomApiConnection":false}},"almMode":"Environment"}}}